{
  "main": {
    "id": "2e9225e34664efd4",
    "type": "split",
    "children": [
      {
        "id": "0571c1c94d829fac",
        "type": "tabs",
        "children": [
          {
            "id": "f41b2a0659b23708",
            "type": "leaf",
            "state": {
              "type": "markdown",
              "state": {
                "file": "Spells/Spells.md",
                "mode": "source",
                "source": false
              },
              "icon": "lucide-file",
              "title": "Spells"
            }
          },
          {
            "id": "54baa124d85df1d3",
            "type": "leaf",
            "state": {
              "type": "markdown",
              "state": {
                "file": "Illusory Script.md",
                "mode": "source",
                "source": false
              },
              "icon": "lucide-file",
              "title": "Illusory Script"
            }
          },
          {
            "id": "8628b15abe8707c3",
            "type": "leaf",
            "state": {
              "type": "markdown",
              "state": {
                "file": "Classes/Warlock.md",
                "mode": "source",
                "source": false
              },
              "icon": "lucide-file",
              "title": "Warlock"
            }
          }
        ],
        "currentTab": 1
      }
    ],
    "direction": "vertical"
  },
  "left": {
    "id": "1243752a4df710bb",
    "type": "split",
    "children": [
      {
        "id": "8a4c81639dc8783e",
        "type": "tabs",
        "children": [
          {
            "id": "b77831b90dd9f87b",
            "type": "leaf",
            "state": {
              "type": "file-explorer",
              "state": {
                "sortOrder": "alphabetical",
                "autoReveal": false
              },
              "icon": "lucide-folder-closed",
              "title": "Files"
            }
          },
          {
            "id": "0829eb50dbb8a2b3",
            "type": "leaf",
            "state": {
              "type": "search",
              "state": {
                "query": "",
                "matchingCase": false,
                "explainSearch": false,
                "collapseAll": false,
                "extraContext": false,
                "sortOrder": "alphabetical"
              },
              "icon": "lucide-search",
              "title": "Search"
            }
          },
          {
            "id": "436d75c49c949463",
            "type": "leaf",
            "state": {
              "type": "bookmarks",
              "state": {},
              "icon": "lucide-bookmark",
              "title": "Bookmarks"
            }
          }
        ]
      }
    ],
    "direction": "horizontal",
    "width": 244.5
  },
  "right": {
    "id": "ba1ec06a672fb227",
    "type": "split",
    "children": [
      {
        "id": "6cea78168fbf9ccd",
        "type": "tabs",
        "children": [
          {
            "id": "2aa5a4c073617928",
            "type": "leaf",
            "state": {
              "type": "backlink",
              "state": {
                "file": "Illusory Script.md",
                "collapseAll": true,
                "extraContext": false,
                "sortOrder": "alphabetical",
                "showSearch": false,
                "searchQuery": "",
                "backlinkCollapsed": false,
                "unlinkedCollapsed": true
              },
              "icon": "links-coming-in",
              "title": "Backlinks for Illusory Script"
            }
          },
          {
            "id": "5acb7020384970a8",
            "type": "leaf",
            "state": {
              "type": "outgoing-link",
              "state": {
                "file": "SPELL-TEMPLATE.md",
                "linksCollapsed": false,
                "unlinkedCollapsed": true
              },
              "icon": "links-going-out",
              "title": "Outgoing links from SPELL-TEMPLATE"
            }
          },
          {
            "id": "f850ba7e9e699bea",
            "type": "leaf",
            "state": {
              "type": "tag",
              "state": {
                "sortOrder": "frequency",
                "useHierarchy": true,
                "showSearch": false,
                "searchQuery": ""
              },
              "icon": "lucide-tags",
              "title": "Tags"
            }
          },
          {
            "id": "2d9129bb8dcf7983",
            "type": "leaf",
            "state": {
              "type": "outline",
              "state": {
                "file": "SPELL-TEMPLATE.md",
                "followCursor": false,
                "showSearch": false,
                "searchQuery": ""
              },
              "icon": "lucide-list",
              "title": "Outline of SPELL-TEMPLATE"
            }
          }
        ]
      }
    ],
    "direction": "horizontal",
    "width": 333.5
  },
  "left-ribbon": {
    "hiddenItems": {
      "bases:Create new base": false,
      "switcher:Open quick switcher": false,
      "graph:Open graph view": false,
      "canvas:Create new canvas": false,
      "daily-notes:Open today's daily note": false,
      "templates:Insert template": false,
      "command-palette:Open command palette": false,
      "obsidian-git:Open Git source control": false
    }
  },
  "active": "54baa124d85df1d3",
  "lastOpenFiles": [
    "Spells/1st Circle Spells/Identify.md",
    "Illusory Script.md",
    "Spells/1st Circle Spells/Ice Knife.md",
    "SPELL-TEMPLATE.md",
    "Spells/1st Circle Spells/Hideous Laughter.md",
    "Spells/1st Circle Spells/Hex.md",
    "Spells/1st Circle Spells/Heroism.md",
    "Spells/1st Circle Spells/Hell’s Lash.md",
    "Spells/1st Circle Spells/Hellish Rebuke.md",
    "Spells/1st Circle Spells/Healing Word.md",
    "Spells/1st Circle Spells/Hail of Thorns.md",
    "Spells/1st Circle Spells/Guiding Bolt.md",
    "Spells/1st Circle Spells/Grease.md",
    "Spells/1st Circle Spells/Goodberry.md",
    "Spells/1st Circle Spells/Gift of Alacrity.md",
    "Spells/1st Circle Spells/Fog Cloud.md",
    "Spells/1st Circle Spells/Floating Disk.md",
    "Spells/1st Circle Spells/Find Familiar.md",
    "Classes/Warlock.md",
    "Spells/Spells.md",
    "Spells/1st Circle Spells/Feather Fall.md",
    "Spells/1st Circle Spells/False Life.md",
    "Spells/1st Circle Spells/Faerie Fire.md",
    "Spells/1st Circle Spells/Expeditious Retreat.md",
    "Spells/1st Circle Spells/Entangle.md",
    "Spells/1st Circle Spells/Ensnaring Strike.md",
    "Spells/1st Circle Spells",
    "Spells/Schools of Magic",
    "Blindness",
    "Spells/Spells.base",
    "The Setting/Higher Powers/Undead Beings",
    "The Setting/Higher Powers/Great Wyrms",
    "The Setting/Higher Powers/Great Old Ones",
    "The Setting/Higher Powers/Elemental Powers",
    "The Setting/Higher Powers/Fiends",
    "The Setting/Higher Powers/Fathomless Beings"
  ]
}